aniparser/__init__.py
aniparser/constants.py
aniparser/parser.py
aniparser/regexes.py
aniparser-0.2.0.dist-info/LICENSE
aniparser-0.2.0.dist-info/METADATA
aniparser-0.2.0.dist-info/WHEEL
aniparser-0.2.0.dist-info/top_level.txt
aniparser-0.2.0.dist-info/RECORD
