Metadata-Version: 2.1
Name: aniparser
Version: 0.2.0
Summary: Provides a parser to parse file names and return data based on the names
Home-page: https://github.com/Phxntxm/aniparser
Author: Dan Hess
Author-email: phxntxm1@gmail.com
License: UNKNOWN
Project-URL: Bug Tracker, https://github.com/Phxntxm/aniparser/issues
Platform: UNKNOWN
Classifier: Programming Language :: Python :: 3
Classifier: License :: OSI Approved :: MIT License
Classifier: Operating System :: OS Independent
Requires-Python: >=3.4
License-File: LICENSE
Requires-Dist: rapidfuzz
